whatsapp_cloud_api/__init__.py
whatsapp_cloud_api/whatsappcloudapi.py
whatsapp_cloud_api-0.0.2.dist-info/METADATA
whatsapp_cloud_api-0.0.2.dist-info/WHEEL
whatsapp_cloud_api-0.0.2.dist-info/licenses/LICENSE
whatsapp_cloud_api-0.0.2.dist-info/RECORD
