Metadata-Version: 2.1
Name: whatsapp-cloud-api
Version: 0.0.2
Summary: WhatsApp Business API Python Library
Project-URL: Homepage, https://github.com/Circuit-Minds/whatsapp-cloud-api
Project-URL: Bug Tracker, https://github.com/Circuit-Minds/whatsapp-cloud-api/issues
Author-email: Shubham Gupta <gshubham533@gmail.com>, Shlok Sawant <shlok.sawant5595@gmail.com>, Suyog Surve <suyog45work@gmail.com>, Shashank Singh <shashank8208@gmail.com>
License-File: LICENSE
Classifier: License :: OSI Approved :: MIT License
Classifier: Operating System :: OS Independent
Classifier: Programming Language :: Python :: 3
Requires-Python: >=3.7
